isrpa/OCR.py
isrpa/Template.py
isrpa/Template_Exception.py
isrpa/__init__.py
isrpa/credentials.py
isrpa/llm_chat.py
isrpa/message.py
isrpa/utils.py
isrpa-1.2.1.dist-info/METADATA
isrpa-1.2.1.dist-info/WHEEL
isrpa-1.2.1.dist-info/top_level.txt
isrpa-1.2.1.dist-info/RECORD
